reverse_attention/__init__.py
reverse_attention/attn_extract.py
reverse_attention/beam.py
reverse_attention/sankey.py
reverse_attention/tokenize.py
reverse_attention/tracer.py
reverse_attention/utils.py
reverse_attention/html/embed.js
reverse_attention/html/sankey_template.html
reverse_attention-0.1.0.dist-info/licenses/LICENSE
reverse_attention-0.1.0.dist-info/METADATA
reverse_attention-0.1.0.dist-info/WHEEL
reverse_attention-0.1.0.dist-info/top_level.txt
reverse_attention-0.1.0.dist-info/RECORD
